swcc/__init__.py
swcc/api.py
swcc/cli.py
swcc/models/__init__.py
swcc/models/api_model.py
swcc/models/constants.py
swcc/models/dataset.py
swcc/models/file.py
swcc/models/other_models.py
swcc/models/project.py
swcc/models/subject.py
swcc/models/utils.py
swcc-1.1.0.dist-info/METADATA
swcc-1.1.0.dist-info/WHEEL
swcc-1.1.0.dist-info/entry_points.txt
swcc-1.1.0.dist-info/top_level.txt
swcc-1.1.0.dist-info/RECORD
