Metadata-Version: 2.1
Name: swcc
Version: 1.1.0
Author: Kitware, Inc.
Author-email: kitware@kitware.com
License: Apache 2.0
Classifier: Development Status :: 3 - Alpha
Classifier: License :: OSI Approved :: Apache Software License
Classifier: Programming Language :: Python :: 3
Classifier: Programming Language :: Python :: 3.8
Classifier: Programming Language :: Python
Requires-Python: >=3.8
Requires-Dist: click <9
Requires-Dist: click-pathlib
Requires-Dist: django-s3-file-field-client <1
Requires-Dist: openpyxl
Requires-Dist: packaging
Requires-Dist: pandas
Requires-Dist: pydantic >=2
Requires-Dist: pyxdg
Requires-Dist: requests
Requires-Dist: requests-toolbelt
Requires-Dist: rich
Requires-Dist: toml
Requires-Dist: tqdm
Requires-Dist: importlib-metadata ; python_version < "3.8"
Requires-Dist: typing-extensions ; python_version < "3.8"
Provides-Extra: dev
Requires-Dist: factory-boy ; extra == 'dev'
Requires-Dist: ipython ; extra == 'dev'
Requires-Dist: tox ; extra == 'dev'
